dumpster/__init__.py
dumpster/api.py
dumpster/cli.py
dumpster/const.py
dumpster/git_utils.py
dumpster/logs.py
dumpster/models.py
dumpster_cli-1.4.0.dist-info/licenses/LICENSE
dumpster_cli-1.4.0.dist-info/METADATA
dumpster_cli-1.4.0.dist-info/WHEEL
dumpster_cli-1.4.0.dist-info/entry_points.txt
dumpster_cli-1.4.0.dist-info/top_level.txt
dumpster_cli-1.4.0.dist-info/RECORD
