Metadata-Version: 2.4
Name: dumpster-cli
Version: 1.4.0
Summary: dump code to single file context like a pro
Requires-Python: >=3.11
License-File: LICENSE
Requires-Dist: gitpython>=3.1.45
Requires-Dist: pydantic>=2.12.5
Requires-Dist: pyyaml>=6.0.3
Requires-Dist: typer>=0.21.0
Dynamic: license-file
